{
    "create_secret_society": {
        "problems": {
            "create_cult": {
                "part_number": "0",
                "method_number": "0",
                "step_number": "7",
                "step_contents": "Invite your friends to a sleepover and then spring it on them. They will be surprised and excited, and thrilled because they are special.",
                "mentions": {
                    "types": {
                        "player": [
                            "friends",
                            "them",
                            "they"
                        ],
                        "secret_society": [
                            "it"
                        ]
                    },
                    "predicates": {
                        "has_secret": [
                            "special"
                        ],
                        "has_info": [
                            "invite"
                        ],
                        "has_name": [
                            "it"
                        ],
                        "has_location": [],
                        "has_dress_code": [],
                        "society_is_ready": [
                            "it"
                        ],
                        "in": [],
                        "is_trusted": [
                            "invite",
                            "friends"
                        ],
                        "equals": [],
                        "friends": [
                            "friends",
                            "them",
                            "they"
                        ],
                        "knows_secret": [
                            "spring"
                        ],
                        "is_cult": [
                            "it"
                        ]
                    },
                    "actions": {
                        "gather_info": [],
                        "create_secret": [],
                        "set_meeting_location": [
                            "sleepover"
                        ],
                        "set_dress_code": [],
                        "create_name": [],
                        "secret_society_is_ready": [],
                        "initiate_new_member": [
                            "invite"
                        ],
                        "teach_new_member_secret": [],
                        "remove_member": [],
                        "check_if_cult": []
                    }
                }
            },
            "remove_players": {
                "part_number": "0",
                "method_number": "0",
                "step_number": "13",
                "step_contents": "There needs to be a way to get rid of someone if they become bad for the group or start talking\u2014like blabbing the society's secret. If they do, pretend like that was never the secret, but immediately create a new secret. Put this in the rules.",
                "mentions": {
                    "types": {
                        "player": [
                            "someone",
                            "they"
                        ],
                        "secret_society": [
                            "group",
                            "society's"
                        ]
                    },
                    "predicates": {
                        "has_secret": [
                            "secret",
                            "blabbing"
                        ],
                        "has_info": [
                            "create"
                        ],
                        "has_name": [],
                        "has_location": [],
                        "has_dress_code": [],
                        "society_is_ready": [],
                        "in": [
                            "group"
                        ],
                        "is_trusted": [
                            "bad",
                            "talking",
                            "blabbing"
                        ],
                        "equals": [],
                        "friends": [],
                        "knows_secret": [
                            "new",
                            "secret",
                            "the secret",
                            "society's secret"
                        ],
                        "is_cult": []
                    },
                    "actions": {
                        "gather_info": [],
                        "create_secret": [],
                        "set_meeting_location": [],
                        "set_dress_code": [],
                        "create_name": [],
                        "secret_society_is_ready": [],
                        "initiate_new_member": [],
                        "teach_new_member_secret": [],
                        "remove_member": [
                            "get rid of",
                            "blabbing the society's secret",
                            "create a new secret",
                            "bad for the group"
                        ],
                        "check_if_cult": []
                    }
                }
            },
            "ready_sc": {
                "part_number": "0",
                "method_number": "0",
                "step_number": "9",
                "step_contents": " Make a dress code. Most small secret societies use robes while large ones, like the Freemasons, have complex aprons. ",
                "mentions": {
                    "types": {
                        "player": [],
                        "secret_society": [
                            "secret societies",
                            "Freemasons"
                        ]
                    },
                    "predicates": {
                        "has_secret": [],
                        "has_info": [],
                        "has_name": [],
                        "has_location": [],
                        "has_dress_code": [
                            "Make a dress code",
                            "robes",
                            "complex aprons",
                            "aprons"
                        ],
                        "society_is_ready": [],
                        "in": [],
                        "is_trusted": [],
                        "equals": [],
                        "friends": [],
                        "knows_secret": [],
                        "is_cult": []
                    },
                    "actions": {
                        "gather_info": [],
                        "create_secret": [],
                        "set_meeting_location": [],
                        "set_dress_code": [],
                        "create_name": [],
                        "secret_society_is_ready": [],
                        "initiate_new_member": [],
                        "teach_new_member_secret": [],
                        "remove_member": [],
                        "check_if_cult": []
                    }
                }
            }
        },
        "wikihow_url": "https://www.wikihow.com/Create-a-Secret-Society",
        "wikihow_title": "How to Create a Secret Society",
        "types": [
            "player",
            "secret_society"
        ],
        "actions": [
            "gather_info",
            "create_secret",
            "set_meeting_location",
            "set_dress_code",
            "create_name",
            "secret_society_is_ready",
            "initiate_new_member",
            "teach_new_member_secret",
            "remove_member",
            "check_if_cult"
        ],
        "predicates": [
            "has_secret",
            "has_info",
            "has_name",
            "has_location",
            "has_dress_code",
            "society_is_ready",
            "in",
            "is_trusted",
            "equals",
            "friends",
            "knows_secret",
            "is_cult"
        ]
    },
    "permissions": {
        "agreed_to_CC-BY": "Yes",
        "name": "Anonymous"
    }
}